sentry_sqs_transport/__init__.py
sentry_sqs_transport-1.0.1.dist-info/LICENSE
sentry_sqs_transport-1.0.1.dist-info/METADATA
sentry_sqs_transport-1.0.1.dist-info/WHEEL
sentry_sqs_transport-1.0.1.dist-info/top_level.txt
sentry_sqs_transport-1.0.1.dist-info/zip-safe
sentry_sqs_transport-1.0.1.dist-info/RECORD
