Metadata-Version: 2.1
Name: sentry-sqs-transport
Version: 1.0.1
Summary: SQS Transport for the sentry-sdk
Home-page: https://github.com/terrycain/sentry-sqs-transport
Author: Terry Cain
Author-email: terry@terrys-home.co.uk
License: Apache 2
Keywords: sentry sqs
Platform: UNKNOWN
Classifier: Development Status :: 2 - Pre-Alpha
Classifier: Intended Audience :: Developers
Classifier: License :: OSI Approved :: Apache Software License
Classifier: Natural Language :: English
Classifier: Programming Language :: Python :: 3
Classifier: Programming Language :: Python :: 3.5
Classifier: Programming Language :: Python :: 3.6
Classifier: Programming Language :: Python :: 3.7
Requires-Python: >=3.6
Requires-Dist: boto3
Requires-Dist: sentry-sdk (>=0.12.2)
